{"botName":"111","overview":{"totalUsers":1,"totalSessions":4,"totalMessages":19,"avgEmotionScore":0.13},"dailyStats":[{"date":"2026-05-17","uniqueUsers":1,"totalSessions":4,"totalMessages":19,"avgEmotionScore":0.13,"topKeywords":[{"keyword":"第一次吃饭","count":2},{"keyword":"你好","count":1},{"keyword":"时间","count":1},{"keyword":"第一次","count":1},{"keyword":"吃饭","count":1},{"keyword":"5月16日","count":1},{"keyword":"忘记","count":1},{"keyword":"测试消息","count":1},{"keyword":"仪表盘","count":1},{"keyword":"消息总数","count":1}],"emotionDistribution":{"neutral":3,"happy":1}}],"recentSessions":[{"id":"ea9cfd88-6f9c-4830-a90a-f96e515564fe","userId":"b69f41cb-39fc-41d7-9b8d-fa677802dd7e","emotion":"neutral","emotionScore":0,"keywords":["第一次吃饭","忘记","测试消息","仪表盘","消息总数"],"summary":"询问第一次吃饭时间，提及测试消息","messageCount":13,"analyzedAt":"2026-05-17T15:50:33.377+00:00"},{"id":"c9eb111c-6990-4ebc-bb21-808cc6178bbb","userId":"b69f41cb-39fc-41d7-9b8d-fa677802dd7e","emotion":"happy","emotionScore":0.5,"keywords":["第一次","吃饭","5月16日"],"summary":"5月16日首次聚餐","messageCount":2,"analyzedAt":"2026-05-17T13:54:22.718592+00:00"},{"id":"1e351400-967c-458c-b365-d1c291f45fb4","userId":"b69f41cb-39fc-41d7-9b8d-fa677802dd7e","emotion":"neutral","emotionScore":0,"keywords":["第一次吃饭","时间"],"summary":"询问第一次吃饭时间","messageCount":2,"analyzedAt":"2026-05-17T13:54:01.666579+00:00"},{"id":"1c4ca622-35c1-4739-9bd0-f4a8f7ff1bfb","userId":"b69f41cb-39fc-41d7-9b8d-fa677802dd7e","emotion":"neutral","emotionScore":0,"keywords":["你好"],"summary":"问候语","messageCount":2,"analyzedAt":"2026-05-17T12:43:05.986503+00:00"}]}